pairwise_combinatorial/__init__.py
pairwise_combinatorial/aggregation.py
pairwise_combinatorial/combinatorial.py
pairwise_combinatorial/gen.py
pairwise_combinatorial/helpers.py
pairwise_combinatorial/llsm.py
pairwise_combinatorial-0.1.2.dist-info/METADATA
pairwise_combinatorial-0.1.2.dist-info/WHEEL
pairwise_combinatorial-0.1.2.dist-info/licenses/LICENSE
pairwise_combinatorial-0.1.2.dist-info/RECORD
