Metadata-Version: 2.4
Name: pairwise-combinatorial
Version: 0.1.2
Summary: Combinatorial method for pairwise comparison aggregation using Prüfer sequences with parallel processing
Project-URL: Homepage, https://github.com/scape76/pairwise-combinatorial
Project-URL: Repository, https://github.com/yourusername/pairwise-combinatorial
Project-URL: Issues, https://github.com/yourusername/pairwise-combinatorial/issues
Author-email: Daniil Olekh <danyaolekhq@gmail.com>
License: MIT
License-File: LICENSE
Keywords: ahp,combinatorial-optimization,decision-making,pairwise-comparison,prufer-sequences
Classifier: Development Status :: 3 - Alpha
Classifier: Intended Audience :: Science/Research
Classifier: License :: OSI Approved :: MIT License
Classifier: Programming Language :: Python :: 3
Classifier: Programming Language :: Python :: 3.11
Classifier: Programming Language :: Python :: 3.12
Classifier: Topic :: Scientific/Engineering :: Mathematics
Requires-Python: >=3.11
Requires-Dist: numpy>=2.3.4
